[{"rank":1,"abbrv":"CHE","country":"Switzerland","eci_value":2.306595,"delta":0,"year":1964},
{"rank":2,"abbrv":"SWE","country":"Sweden","eci_value":2.2507,"delta":0,"year":1964},
{"rank":3,"abbrv":"AUT","country":"Austria","eci_value":2.209263,"delta":0,"year":1964},
{"rank":4,"abbrv":"GBR","country":"United Kingdom","eci_value":2.16646,"delta":0,"year":1964},
{"rank":5,"abbrv":"JPN","country":"Japan","eci_value":2.115119,"delta":0,"year":1964},
{"rank":6,"abbrv":"FRA","country":"France","eci_value":2.019153,"delta":0,"year":1964},
{"rank":7,"abbrv":"USA","country":"United States","eci_value":2.013119,"delta":0,"year":1964},
{"rank":8,"abbrv":"ITA","country":"Italy","eci_value":1.940263,"delta":0,"year":1964},
{"rank":9,"abbrv":"BEL","country":"Belgium","eci_value":1.881067,"delta":0,"year":1964},
{"rank":10,"abbrv":"NOR","country":"Norway","eci_value":1.730345,"delta":0,"year":1964},
{"rank":1,"abbrv":"CHE","country":"Switzerland","eci_value":2.23743,"delta":0,"year":1965},
{"rank":2,"abbrv":"SWE","country":"Sweden","eci_value":2.192915,"delta":0,"year":1965},
{"rank":3,"abbrv":"AUT","country":"Austria","eci_value":2.190211,"delta":0,"year":1965},
{"rank":4,"abbrv":"GBR","country":"United Kingdom","eci_value":2.184238,"delta":0,"year":1965},
{"rank":5,"abbrv":"JPN","country":"Japan","eci_value":2.150768,"delta":0,"year":1965},
{"rank":6,"abbrv":"FRA","country":"France","eci_value":2.033228,"delta":0,"year":1965},
{"rank":7,"abbrv":"USA","country":"United States","eci_value":1.985333,"delta":0,"year":1965},
{"rank":8,"abbrv":"ITA","country":"Italy","eci_value":1.961667,"delta":0,"year":1965},
{"rank":9,"abbrv":"BEL","country":"Belgium","eci_value":1.892022,"delta":0,"year":1965},
{"rank":10,"abbrv":"NOR","country":"Norway","eci_value":1.70788,"delta":0,"year":1965},
{"rank":11,"abbrv":"NLD","country":"Netherlands","eci_value":1.663704,"delta":2,"year":1965},
{"rank":1,"abbrv":"SWE","country":"Sweden","eci_value":2.073687,"delta":1,"year":1966},
{"rank":2,"abbrv":"CHE","country":"Switzerland","eci_value":2.042921,"delta":-1,"year":1966},
{"rank":3,"abbrv":"JPN","country":"Japan","eci_value":2.032553,"delta":2,"year":1966},
{"rank":4,"abbrv":"GBR","country":"United Kingdom","eci_value":2.027595,"delta":0,"year":1966},
{"rank":5,"abbrv":"AUT","country":"Austria","eci_value":2.018466,"delta":-2,"year":1966},
{"rank":6,"abbrv":"FRA","country":"France","eci_value":1.851116,"delta":0,"year":1966},
{"rank":7,"abbrv":"USA","country":"United States","eci_value":1.838381,"delta":0,"year":1966},
{"rank":8,"abbrv":"ITA","country":"Italy","eci_value":1.830155,"delta":0,"year":1966},
{"rank":9,"abbrv":"BEL","country":"Belgium","eci_value":1.742929,"delta":0,"year":1966},
{"rank":10,"abbrv":"NOR","country":"Norway","eci_value":1.729181,"delta":0,"year":1966}]